{
    "steps": [
        {
            "step_number": 1,
            "tool_name": "Facing Tool",
            "tool_speed": "800 RPM",
            "description": "Mount the 65mm diameter bar in the chuck with approximately 125mm protruding. Face the end of the bar to create a flat reference surface at Z=0."
        },
        {
            "step_number": 2,
            "tool_name": "Turning Tool",
            "tool_speed": "800 RPM",
            "description": "Perform a rough turning operation to reduce the outer diameter from 65mm to 60mm over a length of 115mm from the faced end."
        },
        {
            "step_number": 3,
            "tool_name": "Step Turning Tool",
            "tool_speed": "1000 RPM",
            "description": "Reduce the diameter to 45mm starting from the front face up to a length of 90mm (leaving the 25mm long \u00d860 section at the back)."
        },
        {
            "step_number": 4,
            "tool_name": "Step Turning Tool",
            "tool_speed": "1200 RPM",
            "description": "Reduce the diameter to 30mm starting from the front face up to a length of 75mm. This prepares the stock for the taper and the smaller steps."
        },
        {
            "step_number": 5,
            "tool_name": "Taper Turning Tool",
            "tool_speed": "1200 RPM",
            "description": "Machine the taper section between the \u00d845 and \u00d830 diameters. The taper begins at 75mm from the front face (\u00d845) and ends at 50mm from the front face (\u00d830), spanning a length of 25mm."
        },
        {
            "step_number": 6,
            "tool_name": "Step Turning Tool",
            "tool_speed": "1500 RPM",
            "description": "Reduce the diameter to 20mm from the front face up to a length of 25mm (accounting for the 10mm \u00d810 section and 15mm \u00d820 section)."
        },
        {
            "step_number": 7,
            "tool_name": "Step Turning Tool",
            "tool_speed": "2000 RPM",
            "description": "Reduce the final section to 10mm diameter for a length of 10mm from the front face."
        },
        {
            "step_number": 8,
            "tool_name": "Chamfering Tool",
            "tool_speed": "1000 RPM",
            "description": "Apply a 1mm x 45-degree chamfer on the outer edge of the \u00d830 section where it meets the \u00d820 step (at Z-25mm)."
        }
    ],
    "all_reasoning_process": "The process began by analyzing the engineering drawing to identify all critical dimensions and features. The part has a total length of 115mm, composed of six distinct sections: a \u00d860 base (25mm), a \u00d845 step (15mm), a taper from \u00d845 to \u00d830 (25mm), a \u00d830 step (25mm), a \u00d820 step (15mm), and a \u00d810 tip (10mm). The raw material is a 65mm diameter cast iron bar, 150mm long, providing ample material for chucking (35mm). \n\nThe machining strategy follows a logical sequence from largest to smallest diameters to maintain maximum part rigidity during heavy metal removal. First, facing is performed to establish a zero datum. Then, the entire length of the part is turned to the maximum diameter (\u00d860). Subsequent step turning operations reduce the diameter progressively from the front face. Specifically, the \u00d845 and \u00d830 sections are created first to define the boundaries for the taper turning operation. The taper is then machined between the 40mm and 65mm marks (measured from the \u00d860 shoulder). Finally, the smallest steps (\u00d820 and \u00d810) are turned, and a 1mm chamfer is applied to the \u00d830 shoulder as specified. No internal drilling or grooving features were identified in the drawing, so those tools were not utilized in the final plan.",
    "step_by_step_plan": "1. Setup: Secure the \u00d865mm x 150mm cast iron bar in a 3-jaw chuck, ensuring at least 120mm is exposed. \n2. Facing: Use a facing tool at 800 RPM to clean the end face, establishing the Z0 coordinate. \n3. Outer Diameter Roughing: Use a turning tool to reduce the stock to \u00d860mm for a length of 115mm. \n4. Primary Step: Turn the section from Z0 to Z-90mm down to \u00d845mm. \n5. Secondary Step: Turn the section from Z0 to Z-75mm down to \u00d830mm. \n6. Tapering: Program a taper move from X30 Z-50 to X45 Z-75. This creates the 25mm long transition. \n7. Front Steps: Turn the section from Z0 to Z-25mm down to \u00d820mm. Then, turn the final 10mm tip (Z0 to Z-10) down to \u00d810mm. \n8. Finishing: Use a chamfering tool to create a 1mm bevel on the edge of the \u00d830 section at the Z-25 position. \n9. Inspection: Verify all longitudinal lengths (10, 15, 25, 25, 15, 25) and diameters (10, 20, 30, 45, 60) against the drawing before parting or removing from the chuck."
}